{
  "type": "FeatureCollection",
  "features": [
    {
      "type": "Feature",
      "properties": {
        "id": "violet",
        "name": "Violet Route (Academic Spine + North Link)",
        "description": "Academic spine approach terminating at shared parking between A and B block corner",
        "color": "#7B2D8E",
        "parkingHub": "B"
      },
      "geometry": {
        "type": "LineString",
        "coordinates": [
          [
            78.1209203,
            17.5877565
          ],
          [
            78.1209210,
            17.5877960
          ],
          [
            78.1209310,
            17.5878344
          ],
          [
            78.1209498,
            17.5878697
          ],
          [
            78.1209765,
            17.5879000
          ],
          [
            78.1210097,
            17.5879237
          ],
          [
            78.1210478,
            17.5879399
          ],
          [
            78.1210888,
            17.5879473
          ],
          [
            78.1211305,
            17.5879457
          ],
          [
            78.1212162,
            17.5879498
          ],
          [
            78.1212597,
            17.5879537
          ],
          [
            78.1213678,
            17.5880097
          ],
          [
            78.1227836,
            17.5887883
          ],
          [
            78.1229103,
            17.5888579
          ],
          [
            78.1234135,
            17.5891395
          ],
          [
            78.1237644,
            17.5893418
          ],
          [
            78.1238305,
            17.5893877
          ],
          [
            78.1238693,
            17.5894303
          ],
          [
            78.1239062,
            17.5894813
          ],
          [
            78.1239556,
            17.5895250
          ],
          [
            78.1240226,
            17.5895704
          ],
          [
            78.1242244,
            17.5896785
          ],
          [
            78.1246925,
            17.5899485
          ],
          [
            78.1247514,
            17.5899848
          ],
          [
            78.1248027,
            17.5900306
          ],
          [
            78.1248426,
            17.5900723
          ],
          [
            78.1249101,
            17.5901728
          ],
          [
            78.1249231,
            17.5902249
          ],
          [
            78.1249320,
            17.5902833
          ],
          [
            78.1249323,
            17.5903710
          ],
          [
            78.1249383,
            17.5906354
          ],
          [
            78.1249361,
            17.5906997
          ],
          [
            78.1249309,
            17.5908496
          ],
          [
            78.1249419,
            17.5909110
          ],
          [
            78.1249812,
            17.5911334
          ],
          [
            78.1250273,
            17.5913559
          ],
          [
            78.1250272,
            17.5913808
          ],
          [
            78.1250237,
            17.5920155
          ],
          [
            78.1250179,
            17.5928477
          ],
          [
            78.1250100,
            17.5930658
          ],
          [
            78.1250051,
            17.5931120
          ],
          [
            78.1250293,
            17.5931594
          ],
          [
            78.1250741,
            17.5932047
          ],
          [
            78.1252271,
            17.5933698
          ],
          [
            78.1252752,
            17.5934205
          ],
          [
            78.1252919,
            17.5934600
          ],
          [
            78.1252885,
            17.5935187
          ],
          [
            78.1252899,
            17.5938609
          ],
          [
            78.1252872,
            17.5941607
          ],
          [
            78.1252817,
            17.5944302
          ],
          [
            78.1252719,
            17.5950868
          ],
          [
            78.1252712,
            17.5952235
          ],
          [
            78.1252697,
            17.5953382
          ],
          [
            78.1252609,
            17.5959623
          ],
          [
            78.1252401,
            17.5964187
          ],
          [
            78.1251847,
            17.5964286
          ],
          [
            78.1251349,
            17.5964539
          ],
          [
            78.1250954,
            17.5964922
          ],
          [
            78.1250697,
            17.5965401
          ],
          [
            78.1250601,
            17.5965930
          ],
          [
            78.1248394,
            17.5965919
          ],
          [
            78.1243381,
            17.5965834
          ],
          [
            78.1238483,
            17.5965743
          ],
          [
            78.1233009,
            17.5965705
          ],
          [
            78.1216204,
            17.5965518
          ],
          [
            78.1216266705801,
            17.595840481828652
          ],
          [
            78.12196608715749,
            17.595276513546974
          ],
          [
            78.12197857915868,
            17.5946513303249
          ],
          [
            78.12237041718072,
            17.594652655763205
          ]
        ]
      }
    },
    {
      "type": "Feature",
      "properties": {
        "id": "red",
        "name": "Red Route (Workshop Loop Corridor)",
        "description": "Workshop loop corridor terminating at shared parking between A and B block corner",
        "color": "#D32F2F",
        "parkingHub": "B"
      },
      "geometry": {
        "type": "LineString",
        "coordinates": [
          [
            78.1209203,
            17.5877565
          ],
          [
            78.1209210,
            17.5877960
          ],
          [
            78.1209310,
            17.5878344
          ],
          [
            78.1209498,
            17.5878697
          ],
          [
            78.1209765,
            17.5879000
          ],
          [
            78.1210097,
            17.5879237
          ],
          [
            78.12101,
            17.587924
          ],
          [
            78.120925,
            17.58804
          ],
          [
            78.120908,
            17.588071
          ],
          [
            78.120897,
            17.588095
          ],
          [
            78.120892,
            17.588127
          ],
          [
            78.120891,
            17.588176
          ],
          [
            78.12089,
            17.588306
          ],
          [
            78.120889,
            17.588353
          ],
          [
            78.120883,
            17.588958
          ],
          [
            78.120875,
            17.589719
          ],
          [
            78.120877,
            17.591991
          ],
          [
            78.121559,
            17.59199
          ],
          [
            78.121561,
            17.592289
          ],
          [
            78.121582,
            17.592307
          ],
          [
            78.121731,
            17.59231
          ],
          [
            78.121725,
            17.592698
          ],
          [
            78.121719,
            17.593283
          ],
          [
            78.121726,
            17.593313
          ],
          [
            78.12173,
            17.593342
          ],
          [
            78.12174,
            17.593381
          ],
          [
            78.121823,
            17.593532
          ],
          [
            78.121952,
            17.593744
          ],
          [
            78.121961,
            17.593771
          ],
          [
            78.121965,
            17.593801
          ],
          [
            78.121963,
            17.593831
          ],
          [
            78.12197,
            17.594396
          ],
          [
            78.12196,
            17.594662614214414
          ],
          [
            78.12258723942493,
            17.594662614214414
          ]
        ]
      }
    }
  ],
  "parkingHubs": {
    "A": {
      "name": "Shared Origin Point (Point A)",
      "coordinates": [
        17.5877565,
        78.1209203
      ],
      "description": "Common origin point for vehicles entering the campus"
    },
    "B": {
      "name": "Shared Parking Destination (A-B Corner)",
      "coordinates": [
        17.594662614214414,
        78.12258723942493
      ],
      "description": "Common endpoint used by both route choices at the parking between A and B block corner"
    }
  }
}